{
    "type": "FeatureCollection",
    "features": [
        {
            "type": "Feature",
            "properties": {},
            "geometry": {
                "type": "Polygon",
                "coordinates": [
                    [
                        [
                            180,
                            90
                        ],
                        [
                            -180,
                            90
                        ],
                        [
                            -180,
                            -90
                        ],
                        [
                            180,
                            -90
                        ],
                        [
                            180,
                            90
                        ]
                    ],
                    [
                        [
                            85.318662,
                            27.683404
                        ],
                        [
                            85.318586,
                            27.683142
                        ],
                        [
                            85.318494,
                            27.682972
                        ],
                        [
                            85.318208,
                            27.682623
                        ],
                        [
                            85.318099,
                            27.682482
                        ],
                        [
                            85.317856,
                            27.681998
                        ],
                        [
                            85.317670,
                            27.681511
                        ],
                        [
                            85.317550,
                            27.681249
                        ],
                        [
                            85.317410,
                            27.680886
                        ],
                        [
                            85.317250,
                            27.680475
                        ],
                        [
                            85.317834,
                            27.680253
                        ],
                        [
                            85.319300,
                            27.679745
                        ],
                        [
                            85.319659,
                            27.679620
                        ],
                        [
                            85.320490,
                            27.679340
                        ],
                        [
                            85.320518,
                            27.679834
                        ],
                        [
                            85.320520,
                            27.680234
                        ],
                        [
                            85.32050,
                            27.68047
                        ],
                        [
                            85.32044,
                            27.68072
                        ],
                        [
                            85.32040,
                            27.68084
                        ],
                        [
                            85.32028,
                            27.68109
                        ],
                        [
                            85.320070,
                            27.681474
                        ],
                        [
                            85.320279,
                            27.681363
                        ],
                        [
                            85.320488,
                            27.681143
                        ],
                        [
                            85.320845,
                            27.680882
                        ],
                        [
                            85.321064,
                            27.680698
                        ],
                        [
                            85.321346,
                            27.680480
                        ],
                        [
                            85.321569,
                            27.680297
                        ],
                        [
                            85.321695,
                            27.680482
                        ],
                        [
                            85.321738,
                            27.680690
                        ],
                        [
                            85.321745,
                            27.680900
                        ],
                        [
                            85.321835,
                            27.681119
                        ],
                        [
                            85.321923,
                            27.681241
                        ],
                        [
                            85.321993,
                            27.681393
                        ],
                        [
                            85.322094,
                            27.681679
                        ],
                        [
                            85.322390,
                            27.681621
                        ],
                        [
                            85.322476,
                            27.681471
                        ],
                        [
                            85.322606,
                            27.681621
                        ],
                        [
                            85.322798,
                            27.681549
                        ],
                        [
                            85.323028,
                            27.681421
                        ],
                        [
                            85.323260,
                            27.681389
                        ],
                        [
                            85.323599,
                            27.681083
                        ],
                        [
                            85.323793,
                            27.681032
                        ],
                        [
                            85.323928,
                            27.681018
                        ],
                        [
                            85.324120,
                            27.681014
                        ],
                        [
                            85.324431,
                            27.681069
                        ],
                        [
                            85.324584,
                            27.681111
                        ],
                        [
                            85.324668,
                            27.681044
                        ],
                        [
                            85.324855,
                            27.681217
                        ],
                        [
                            85.325035,
                            27.681487
                        ],
                        [
                            85.325315,
                            27.681745
                        ],
                        [
                            85.325429,
                            27.681936
                        ],
                        [
                            85.325536,
                            27.682181
                        ],
                        [
                            85.32560,
                            27.68234
                        ],
                        [
                            85.325697,
                            27.682625
                        ],
                        [
                            85.325748,
                            27.682796
                        ],
                        [
                            85.325844,
                            27.683010
                        ],
                        [
                            85.325655,
                            27.683060
                        ],
                        [
                            85.325456,
                            27.683109
                        ],
                        [
                            85.325293,
                            27.683169
                        ],
                        [
                            85.325155,
                            27.683245
                        ],
                        [
                            85.324992,
                            27.683344
                        ],
                        [
                            85.32487,
                            27.68341
                        ],
                        [
                            85.32489,
                            27.68340
                        ],
                        [
                            85.324732,
                            27.683480
                        ],
                        [
                            85.324565,
                            27.683549
                        ],
                        [
                            85.324474,
                            27.683579
                        ],
                        [
                            85.324328,
                            27.683547
                        ],
                        [
                            85.324227,
                            27.683503
                        ],
                        [
                            85.324017,
                            27.683582
                        ],
                        [
                            85.323764,
                            27.683685
                        ],
                        [
                            85.323510,
                            27.683777
                        ],
                        [
                            85.323357,
                            27.683826
                        ],
                        [
                            85.323239,
                            27.683868
                        ],
                        [
                            85.323169,
                            27.684027
                        ],
                        [
                            85.32310,
                            27.68417
                        ],
                        [
                            85.32293,
                            27.68441
                        ],
                        [
                            85.322737,
                            27.684449
                        ],
                        [
                            85.322573,
                            27.684486
                        ],
                        [
                            85.322427,
                            27.684548
                        ],
                        [
                            85.322352,
                            27.684435
                        ],
                        [
                            85.322219,
                            27.684313
                        ],
                        [
                            85.322160,
                            27.684333
                        ],
                        [
                            85.322126,
                            27.684299
                        ],
                        [
                            85.322084,
                            27.684311
                        ],
                        [
                            85.322006,
                            27.684338
                        ],
                        [
                            85.321947,
                            27.684355
                        ],
                        [
                            85.321843,
                            27.684264
                        ],
                        [
                            85.321730,
                            27.684170
                        ],
                        [
                            85.321617,
                            27.684043
                        ],
                        [
                            85.321479,
                            27.684110
                        ],
                        [
                            85.321338,
                            27.684163
                        ],
                        [
                            85.321133,
                            27.684226
                        ],
                        [
                            85.320968,
                            27.684239
                        ],
                        [
                            85.320864,
                            27.684240
                        ],
                        [
                            85.320830,
                            27.684154
                        ],
                        [
                            85.320751,
                            27.684157
                        ],
                        [
                            85.320679,
                            27.684040
                        ],
                        [
                            85.320534,
                            27.684021
                        ],
                        [
                            85.320350,
                            27.684002
                        ],
                        [
                            85.320344,
                            27.683834
                        ],
                        [
                            85.320333,
                            27.683665
                        ],
                        [
                            85.320164,
                            27.683601
                        ],
                        [
                            85.319912,
                            27.683586
                        ],
                        [
                            85.319714,
                            27.683507
                        ],
                        [
                            85.319539,
                            27.683341
                        ],
                        [
                            85.319416,
                            27.683214
                        ],
                        [
                            85.319180,
                            27.683102
                        ],
                        [
                            85.319062,
                            27.683050
                        ],
                        [
                            85.318952,
                            27.683223
                        ],
                        [
                            85.318891,
                            27.683349
                        ],
                        [
                            85.318662,
                            27.683404
                        ]
                    ]
                ]
            }
        },
        {
            "type": "Feature",
            "properties": {
                "description": "ICTC Bulding"
            },
            "geometry": {
                "type": "Point",
                "coordinates": [
                    85.31925432667049,
                    27.68227948566954
                ]
            }
        },
        {
            "type": "Feature",
            "properties": {
                "description": "Campus Mess"
            },
            "geometry": {
                "type": "Point",
                "coordinates": [
                    85.31958339939047,
                    27.680813732882058
                ]
            }
        },
        {
            "type": "Feature",
            "properties": {
                "description": "Dean Office"
            },
            "geometry": {
                "type": "Point",
                "coordinates": [
                    85.31875195490352,
                    27.68095603886991
                ]
            }
        },
        {
            "type": "Feature",
            "properties": {
                "description": "Department of Architecture"
            },
            "geometry": {
                "type": "Point",
                "coordinates": [
                    85.31831152476735,
                    27.68044934237453
                ]
            }
        },
        {
            "type": "Feature",
            "properties": {
                "description": "ASA Office"
            },
            "geometry": {
                "type": "Point",
                "coordinates": [
                    85.31840952112645,
                    27.680433693360456
                ]
            }
        },
        {
            "type": "Feature",
            "properties": {
                "description": "MSC Hostel"
            },
            "geometry": {
                "type": "Point",
                "coordinates": [
                    85.319017191439,
                    27.680091477233432
                ]
            }
        },
        {
            "type": "Feature",
            "properties": {
                "description": "Hydro Lab"
            },
            "geometry": {
                "type": "Point",
                "coordinates": [
                    85.31942804361722,
                    27.68018924241545
                ]
            }
        },
        {
            "type": "Feature",
            "properties": {
                "description": "Department of Roads"
            },
            "geometry": {
                "type": "Point",
                "coordinates": [
                    85.31990450135862,
                    27.68073700031121
                ]
            }
        },
        {
            "type": "Feature",
            "properties": {
                "description": "Locus Office"
            },
            "geometry": {
                "type": "Point",
                "coordinates": [
                    85.3185504866151,
                    27.68139565322535
                ]
            }
        },
        {
            "type": "Feature",
            "properties": {
                "description": "Department of Electrical, Electronics and Computer Engineering"
            },
            "geometry": {
                "type": "Point",
                "coordinates": [
                    85.31875628492219,
                    27.68182260516565
                ]
            }
        },
        {
            "type": "Feature",
            "properties": {
                "description": "Robotics Club"
            },
            "geometry": {
                "type": "Point",
                "coordinates": [
                    85.31901450533206,
                    27.68136224565515
                ]
            }
        },
        {
            "type": "Feature",
            "properties": {
                "description": "Continuing Education Center"
            },
            "geometry": {
                "type": "Point",
                "coordinates": [
                    85.31895314397525,
                    27.681494777843028
                ]
            }
        },
        {
            "type": "Feature",
            "properties": {
                "description": "Pulchowk Library"
            },
            "geometry": {
                "type": "Point",
                "coordinates": [
                    85.31944424082258,
                    27.681616524851407
                ]
            }
        },
        {
            "type": "Feature",
            "properties": {
                "description": "Electrical Club"
            },
            "geometry": {
                "type": "Point",
                "coordinates": [
                    85.3182927681815,
                    27.682291135732115
                ]
            }
        },
        {
            "type": "Feature",
            "properties": {
                "description": "Block C"
            },
            "geometry": {
                "type": "Point",
                "coordinates": [
                    85.31833975128347,
                    27.682140047755496
                ]
            }
        },
        {
            "type": "Feature",
            "properties": {
                "description": "ICT Bulding"
            },
            "geometry": {
                "type": "Point",
                "coordinates": [
                    85.31914285425017,
                    27.681715172918075
                ]
            }
        },
        {
            "type": "Feature",
            "properties": {
                "description": "Embark College"
            },
            "geometry": {
                "type": "Point",
                "coordinates": [
                    85.31888939994957,
                    27.682712891619232
                ]
            }
        },
        {
            "type": "Feature",
            "properties": {
                "description": "Nabil Bank ATM"
            },
            "geometry": {
                "type": "Point",
                "coordinates": [
                    85.31853678585821,
                    27.682829607001196
                ]
            }
        },
        {
            "type": "Feature",
            "properties": {
                "description": "Siddhartha Bank ATM"
            },
            "geometry": {
                "type": "Point",
                "coordinates": [
                    85.31945726206425,
                    27.68210633185008
                ]
            }
        },
        {
            "type": "Feature",
            "properties": {
                "description": "Heavy Lab"
            },
            "geometry": {
                "type": "Point",
                "coordinates": [
                    85.32044738817302,
                    27.68209387245163
                ]
            }
        },
        {
            "type": "Feature",
            "properties": {
                "description": "Parking"
            },
            "geometry": {
                "type": "Point",
                "coordinates": [
                    85.31992845601593,
                    27.68214769544541
                ]
            }
        },
        {
            "type": "Feature",
            "properties": {
                "description": "Helicopter Parking"
            },
            "geometry": {
                "type": "Point",
                "coordinates": [
                    85.31973837978478,
                    27.682269017217237
                ]
            }
        },
        {
            "type": "Feature",
            "properties": {
                "description": "PI Chautari"
            },
            "geometry": {
                "type": "Point",
                "coordinates": [
                    85.31987844126758,
                    27.68267661712244
                ]
            }
        },
        {
            "type": "Feature",
            "properties": {
                "description": "Department of Mechanical and Aerospace Engineering"
            },
            "geometry": {
                "type": "Point",
                "coordinates": [
                    85.31986930605723,
                    27.682462244093173
                ]
            }
        },
        {
            "type": "Feature",
            "properties": {
                "description": "Saraswati Mandir"
            },
            "geometry": {
                "type": "Point",
                "coordinates": [
                    85.31939527713587,
                    27.68256455316562
                ]
            }
        },
        {
            "type": "Feature",
            "properties": {
                "description": "Department of Civil Engineering"
            },
            "geometry": {
                "type": "Point",
                "coordinates": [
                    85.31936398409704,
                    27.682968475303554
                ]
            }
        },
        {
            "type": "Feature",
            "properties": {
                "description": "F Block"
            },
            "geometry": {
                "type": "Point",
                "coordinates": [
                    85.3196061234986,
                    27.682788668714352
                ]
            }
        },
        {
            "type": "Feature",
            "properties": {
                "description": "Department of Mechanical and Aerospace Engineering"
            },
            "geometry": {
                "type": "Point",
                "coordinates": [
                    85.32078190861336,
                    27.682393906140106
                ]
            }
        },
        {
            "type": "Feature",
            "properties": {
                "description": "The Helm of IOE Pulchowk"
            },
            "geometry": {
                "type": "Point",
                "coordinates": [
                    85.32083316993328,
                    27.682629953546424
                ]
            }
        },
        {
            "type": "Feature",
            "properties": {
                "description": "FSU Office"
            },
            "geometry": {
                "type": "Point",
                "coordinates": [
                    85.3207254626837,
                    27.682902435847012
                ]
            }
        },
        {
            "type": "Feature",
            "properties": {
                "description": "NTBNS"
            },
            "geometry": {
                "type": "Point",
                "coordinates": [
                    85.32070525005736,
                    27.683007442872864
                ]
            }
        },
        {
            "type": "Feature",
            "properties": {
                "description": "Department of Applied Sciences and Chemical Engineering"
            },
            "geometry": {
                "type": "Point",
                "coordinates": [
                    85.3203848726879,
                    27.682935941133437
                ]
            }
        },
        {
            "type": "Feature",
            "properties": {
                "description": "Department of Applied Sciences and chemical engineering"
            },
            "geometry": {
                "type": "Point",
                "coordinates": [
                    85.3200449911119,
                    27.683220527000756
                ]
            }
        },
        {
            "type": "Feature",
            "properties": {
                "description": "G Block"
            },
            "geometry": {
                "type": "Point",
                "coordinates": [
                    85.32018128025857,
                    27.68310430877834
                ]
            }
        },
        {
            "type": "Feature",
            "properties": {
                "description": "CIDS"
            },
            "geometry": {
                "type": "Point",
                "coordinates": [
                    85.31990266456802,
                    27.683010663794747
                ]
            }
        },
        {
            "type": "Feature",
            "properties": {
                "description": "Department of Science and Humanities"
            },
            "geometry": {
                "type": "Point",
                "coordinates": [
                    85.32054395296416,
                    27.683041212054775
                ]
            }
        },
        {
            "type": "Feature",
            "properties": {
                "description": "Second Entrance"
            },
            "geometry": {
                "type": "Point",
                "coordinates": [
                    85.31773353764987,
                    27.681380190252256
                ]
            }
        },
        {
            "type": "Feature",
            "properties": {
                "description": "First Entrance"
            },
            "geometry": {
                "type": "Point",
                "coordinates": [
                    85.3194594635064,
                    27.68207456812752
                ]
            }
        },
        {
            "type": "Feature",
            "properties": {
                "description": "Hydropower Testing Lab"
            },
            "geometry": {
                "type": "Point",
                "coordinates": [
                    85.32052846482077,
                    27.68346942813116
                ]
            }
        },
        {
            "type": "Feature",
            "properties": {
                "description": "SEDS Pulchowk"
            },
            "geometry": {
                "type": "Point",
                "coordinates": [
                    85.32041220727473,
                    27.683617545231883
                ]
            }
        },
        {
            "type": "Feature",
            "properties": {
                "description": "Center for Energy Studies"
            },
            "geometry": {
                "type": "Point",
                "coordinates": [
                    85.3208610299663,
                    27.68321662681744
                ]
            }
        },
        {
            "type": "Feature",
            "properties": {
                "description": "Pulchowk Cricket Ground"
            },
            "geometry": {
                "type": "Point",
                "coordinates": [
                    85.32215173345384,
                    27.683328511076553
                ]
            }
        },
        {
            "type": "Feature",
            "properties": {
                "description": "Pulchowk Football Ground"
            },
            "geometry": {
                "type": "Point",
                "coordinates": [
                    85.322933342042,
                    27.682630231202694
                ]
            }
        },
        {
            "type": "Feature",
            "properties": {
                "description": "Pulchowk Volleyball Court"
            },
            "geometry": {
                "type": "Point",
                "coordinates": [
                    85.3232165987614,
                    27.682254992538773
                ]
            }
        },
        {
            "type": "Feature",
            "properties": {
                "description": "Cricket Practice Pitch"
            },
            "geometry": {
                "type": "Point",
                "coordinates": [
                    85.32345024929077,
                    27.682835875995877
                ]
            }
        },
        {
            "type": "Feature",
            "properties": {
                "description": "Basketball Court"
            },
            "geometry": {
                "type": "Point",
                "coordinates": [
                    85.32258776220266,
                    27.681816863769555
                ]
            }
        },
        {
            "type": "Feature",
            "properties": {
                "description": "Block A Pulchowk Boys Hostel"
            },
            "geometry": {
                "type": "Point",
                "coordinates": [
                    85.3239283186274,
                    27.682188311416212
                ]
            }
        },
        {
            "type": "Feature",
            "properties": {
                "description": "Block B Pulchowk Boys Hostel"
            },
            "geometry": {
                "type": "Point",
                "coordinates": [
                    85.32390377692212,
                    27.68184284511355
                ]
            }
        },
        {
            "type": "Feature",
            "properties": {
                "description": "Block C Pulchowk Boys Hostel"
            },
            "geometry": {
                "type": "Point",
                "coordinates": [
                    85.32390894588298,
                    27.681485585500837
                ]
            }
        },
        {
            "type": "Feature",
            "properties": {
                "description": "Niraula Stores"
            },
            "geometry": {
                "type": "Point",
                "coordinates": [
                    85.32321651934609,
                    27.681833530683008
                ]
            }
        },
        {
            "type": "Feature",
            "properties": {
                "description": "Calisthenics park, Outdoor Gym"
            },
            "geometry": {
                "type": "Point",
                "coordinates": [
                    85.32277525891658,
                    27.68190370401871
                ]
            }
        },
        {
            "type": "Feature",
            "properties": {
                "description": "Chemical Engineering Lab"
            },
            "geometry": {
                "type": "Point",
                "coordinates": [
                    85.32328685569604,
                    27.681784531262693
                ]
            }
        },
        {
            "type": "Feature",
            "properties": {
                "description": "Pulchowk Gym Hall"
            },
            "geometry": {
                "type": "Point",
                "coordinates": [
                    85.32348549458561,
                    27.68144851050316
                ]
            }
        },
        {
            "type": "Feature",
            "properties": {
                "description": "Campus Canteen"
            },
            "geometry": {
                "type": "Point",
                "coordinates": [
                    85.32354899843239,
                    27.68125093458133
                ]
            }
        },
        {
            "type": "Feature",
            "properties": {
                "description": "Pulchowk Music Club"
            },
            "geometry": {
                "type": "Point",
                "coordinates": [
                    85.32322012669403,
                    27.6816237436294
                ]
            }
        },
        {
            "type": "Feature",
            "properties": {
                "description": "Pulchowk Girls Hostel"
            },
            "geometry": {
                "type": "Point",
                "coordinates": [
                    85.3240672595856,
                    27.683199124783584
                ]
            }
        },
        {
            "type": "Feature",
            "properties": {
                "description": "Pulchowk Teacher's Quarter"
            },
            "geometry": {
                "type": "Point",
                "coordinates": [
                    85.324714775784,
                    27.683030311890363
                ]
            }
        },
        {
            "type": "Feature",
            "properties": {
                "description": "Staff Quarter"
            },
            "geometry": {
                "type": "Point",
                "coordinates": [
                    85.32411254835387,
                    27.68249831633632
                ]
            }
        },
        {
            "type": "Feature",
            "properties": {
                "description": "Exam Control Office, IOE"
            },
            "geometry": {
                "type": "Point",
                "coordinates": [
                    85.32103017170311,
                    27.681071855710286
                ]
            }
        },
        {
            "type": "Feature",
            "properties": {
                "description": "Om Stationery Store"
            },
            "geometry": {
                "type": "Point",
                "coordinates": [
                    85.31984862292666,
                    27.681843392083223
                ]
            }
        },
        {
            "type": "Feature",
            "properties": {
                "description": "E Block"
            },
            "geometry": {
                "type": "Point",
                "coordinates": [
                    85.31843868135616,
                    27.680606526940423
                ]
            }
        },
        {
            "type": "Feature",
            "properties": {
                "description": "D Block"
            },
            "geometry": {
                "type": "Point",
                "coordinates": [
                    85.3200115923417,
                    27.68247103573296
                ]
            }
        },
        {
            "type": "Feature",
            "properties": {
                "description": "FSU Clinic"
            },
            "geometry": {
                "type": "Point",
                "coordinates": [
                    85.31924168355874,
                    27.681570244524437
                ]
            }
        },
        {
            "type": "Feature",
            "properties": {
                "description": "Badminton Court"
            },
            "geometry": {
                "type": "Point",
                "coordinates": [
                    85.31850453478063,
                    27.68195320004999
                ]
            }
        }
    ]
}